Metadata-Version: 1.0
Name: wirereport
Version: 2022.3.2.1820
Summary: a small text editor
Home-page: https://github.com/wdbm/report
Author: Will Breaden Madden
Author-email: wbm@protonmail.ch
License: GPLv3
Platform: UNKNOWN
